qase/behave/__init__.py
qase/behave/formatter.py
qase/behave/qase_global.py
qase/behave/utils.py
qase_behave-3.0.0.dist-info/licenses/LICENSE.txt
qase_behave-3.0.0.dist-info/METADATA
qase_behave-3.0.0.dist-info/WHEEL
qase_behave-3.0.0.dist-info/top_level.txt
qase_behave-3.0.0.dist-info/RECORD
